{"created_ts": 1766756893.9758272, "payload": [{"ArchiveDate": "2024-12-21", "Season": 2025, "Preseason": "false", "TeamName": "Mount St. Mary's", "Seed": 16, "Event": "NCAA", "ConfShort": "MAAC", "AdjEM": -7.3687, "RankAdjEM": 253, "AdjOE": 101.457, "RankAdjOE": 276, "AdjDE": 108.825, "RankAdjDE": 214, "AdjTempo": 69.0908, "RankAdjTempo": 140, "AdjEMFinal": -6.3416, "RankAdjEMFinal": 243, "AdjOEFinal": 100.939, "RankAdjOEFinal": 283, "AdjDEFinal": 107.281, "RankAdjDEFinal": 186, "AdjTempoFinal": 67.7997, "RankAdjTempoFinal": 160, "RankChg": 10, "AdjEMChg": 1.0271, "AdjTChg": -1.2911}]}