{"created_ts": 1766758691.0911849, "payload": [{"ArchiveDate": "2025-12-21", "Season": 2026, "Preseason": "false", "TeamName": "Vanderbilt", "Seed": 0, "Event": null, "ConfShort": "SEC", "AdjEM": 27.434, "RankAdjEM": 10, "AdjOE": 123.619, "RankAdjOE": 11, "AdjDE": 96.1847, "RankAdjDE": 17, "AdjTempo": 72.0182, "RankAdjTempo": 42, "AdjEMFinal": 29.6916, "RankAdjEMFinal": 8, "AdjOEFinal": 125.418, "RankAdjOEFinal": 8, "AdjDEFinal": 95.7263, "RankAdjDEFinal": 14, "AdjTempoFinal": 71.9388, "RankAdjTempoFinal": 44, "RankChg": 2, "AdjEMChg": 2.2576, "AdjTChg": -0.0794}]}