{"created_ts": 1766756905.9772818, "payload": [{"ArchiveDate": "2024-12-21", "Season": 2025, "Preseason": "false", "TeamName": "Northern Colorado", "Seed": 0, "Event": null, "ConfShort": "BSky", "AdjEM": -0.8213, "RankAdjEM": 168, "AdjOE": 107.899, "RankAdjOE": 147, "AdjDE": 108.721, "RankAdjDE": 211, "AdjTempo": 71.8157, "RankAdjTempo": 32, "AdjEMFinal": 3.6323, "RankAdjEMFinal": 126, "AdjOEFinal": 112.211, "RankAdjOEFinal": 86, "AdjDEFinal": 108.579, "RankAdjDEFinal": 210, "AdjTempoFinal": 68.9111, "RankAdjTempoFinal": 96, "RankChg": 42, "AdjEMChg": 4.4537, "AdjTChg": -2.9046}]}